pocketlab/__init__.py
pocketlab/__main__.py
pocketlab/cli.py
pocketlab/init.py
pocketlab/parser.py
pocketlab/utils.py
pocketlab/commands/__init__.py
pocketlab/commands/clean.py
pocketlab/commands/connect.py
pocketlab/commands/deploy.py
pocketlab/commands/get.py
pocketlab/commands/home.py
pocketlab/commands/init.py
pocketlab/commands/install.py
pocketlab/commands/launch.py
pocketlab/commands/list.py
pocketlab/commands/put.py
pocketlab/commands/remove.py
pocketlab/commands/start.py
pocketlab/commands/update.py
pocketlab/methods/__init__.py
pocketlab/methods/aws.py
pocketlab/methods/certbot.py
pocketlab/methods/config.py
pocketlab/methods/dependencies.py
pocketlab/methods/docker.py
pocketlab/methods/heroku.py
pocketlab/methods/nginx.py
pocketlab/methods/node.py
pocketlab/methods/service.py
pocketlab/methods/validation.py
pocketlab/methods/vcs.py
pocketlab/models/asg-config.json
pocketlab/models/aws-config.json
pocketlab/models/babelrc.txt
pocketlab/models/certbot-install.json
pocketlab/models/changelog.md.txt
pocketlab/models/changes.rst.txt
pocketlab/models/compose-config.json
pocketlab/models/content.html
pocketlab/models/coveralls.yml.txt
pocketlab/models/docker-install.json
pocketlab/models/docker.readme.md.txt
pocketlab/models/dockerignore.txt
pocketlab/models/docsify.index.html.txt
pocketlab/models/ec2-config.json
pocketlab/models/express.dockerfile.txt
pocketlab/models/express.gulpfile.js.txt
pocketlab/models/express.package.json
pocketlab/models/favicon.ico
pocketlab/models/flask.dockerfile.txt
pocketlab/models/flask.requirements.txt
pocketlab/models/footer.html
pocketlab/models/gae.app.yaml.txt
pocketlab/models/gae.requirements.txt
pocketlab/models/gcloudignore.txt
pocketlab/models/gitignore.node.txt
pocketlab/models/gitignore.python.txt
pocketlab/models/gitignore.service.txt
pocketlab/models/header.html
pocketlab/models/heroku-config.json
pocketlab/models/jquery.global.dependencies.json
pocketlab/models/jquery.package.json
pocketlab-0.12.dist-info/LICENSE.txt
pocketlab-0.12.dist-info/METADATA
pocketlab-0.12.dist-info/WHEEL
pocketlab-0.12.dist-info/entry_points.txt
pocketlab-0.12.dist-info/top_level.txt
pocketlab-0.12.dist-info/RECORD
