Metadata-Version: 2.1
Name: pocketlab
Version: 0.12
Summary: A Command Line Tool for Managing Laboratory Projects
Home-page: https://github.com/collectiveacuity/pocketLab
Author: rcj1492
Author-email: support@collectiveacuity.com
Maintainer-email: support@collectiveacuity.com
License: MIT
Platform: UNKNOWN
Classifier: Development Status :: 3 - Alpha
Classifier: Environment :: Web Environment
Classifier: Intended Audience :: Developers
Classifier: License :: OSI Approved :: MIT License
Classifier: Natural Language :: English
Classifier: Programming Language :: Python
Classifier: Programming Language :: Python :: 3.5
Classifier: Programming Language :: Python :: 3.6
Requires-Dist: jsonmodel
Requires-Dist: labpack
Requires-Dist: tabulate (>=0.7.7)
Requires-Dist: ruamel.yaml (>=0.14.12)
Requires-Dist: pexpect
Requires-Dist: colorama
